gnupg-2.2.0.data/scripts/versioneer.py
gnupg/copyleft.py
gnupg/__init__.py
gnupg/gnupg.py
gnupg/_meta.py
gnupg/_version.py
gnupg/_logger.py
gnupg/_parsers.py
gnupg/_util.py
gnupg/_ansistrm.py
gnupg/_trust.py
gnupg-2.2.0.dist-info/METADATA
gnupg-2.2.0.dist-info/metadata.json
gnupg-2.2.0.dist-info/DESCRIPTION.rst
gnupg-2.2.0.dist-info/top_level.txt
gnupg-2.2.0.dist-info/RECORD
gnupg-2.2.0.dist-info/WHEEL
